{
  "artifact_type": "certification_record",
  "schema_version": "1.0.0",
  "trace_id": "trace-bne02-004",
  "run_id": "run-bne02-004",
  "verdict": "CERTIFIED",
  "checks": {
    "eval_coverage": true,
    "promotion_gates": true,
    "policy_enforcement": true,
    "context_integrity": true,
    "drift_control": true
  },
  "redteam_findings": [
    {
      "finding_id": "RTX-13-1",
      "status": "fixed"
    }
  ],
  "fixes": [
    {
      "finding_id": "RTX-13-1",
      "fix_id": "FIX-13-RTX-13-1"
    }
  ],
  "remaining_risks": []
}
